browsergym/webarenalite/__init__.py
browsergym/webarenalite/config.py
browsergym/webarenalite/evaluators.py
browsergym/webarenalite/helper_functions.py
browsergym/webarenalite/task.py
browsergym/webarenalite/test_webarena_lite.raw.json
browsergym_webarenalite-0.14.3.dist-info/METADATA
browsergym_webarenalite-0.14.3.dist-info/WHEEL
browsergym_webarenalite-0.14.3.dist-info/RECORD
