Metadata-Version: 2.4
Name: browsergym-webarenalite
Version: 0.14.3
Summary: WebArena Lite benchmark for BrowserGym
Project-URL: homepage, https://github.com/ServiceNow/BrowserGym
Author: Aman Jaiswal, Leo Biosvert
License: Apache-2.0
Classifier: Development Status :: 3 - Alpha
Classifier: Intended Audience :: Science/Research
Classifier: License :: OSI Approved :: Apache Software License
Classifier: Operating System :: OS Independent
Classifier: Programming Language :: Python :: 3
Classifier: Topic :: Scientific/Engineering :: Artificial Intelligence
Requires-Python: >3.7
Requires-Dist: browsergym-core==0.14.3
Requires-Dist: browsergym-webarena==0.14.3
Requires-Dist: libwebarena==0.0.4
